cli.py
app/__init__.py
app/cli_logging.py
app/config.py
app/logging_config.py
app/main.py
app/run.py
app/validator.py
demo/__init__.py
demo/cli.py
demo/scenarios.py
demo/fixtures/clients.json
demo/fixtures/pools.json
proxycall/__init__.py
proxycall/__main__.py
proxycall_cli-0.1.3.dist-info/METADATA
proxycall_cli-0.1.3.dist-info/WHEEL
proxycall_cli-0.1.3.dist-info/entry_points.txt
proxycall_cli-0.1.3.dist-info/top_level.txt
proxycall_cli-0.1.3.dist-info/RECORD
