Metadata-Version: 2.4
Name: proxycall-cli
Version: 0.1.3
Summary: CLI ProxyCall légère pour piloter l'API en local ou sur Render
Author: Équipe ProxyCall
Project-URL: Homepage, https://github.com/user/project
Requires-Python: >=3.10
Requires-Dist: httpx>=0.25
Requires-Dist: python-dotenv>=1.0
Requires-Dist: rich>=13.0
Provides-Extra: twilio
Requires-Dist: twilio>=9; extra == "twilio"
Provides-Extra: gsheets
Requires-Dist: gspread>=5; extra == "gsheets"
Requires-Dist: google-auth>=2; extra == "gsheets"
Provides-Extra: dev
Requires-Dist: build>=1.0; extra == "dev"
Requires-Dist: twine>=5.0; extra == "dev"
